asyncio_cache/__init__.py
asyncio_cache/asyncio_cache.py
asyncio_cache-0.0.1.dist-info/LICENSE
asyncio_cache-0.0.1.dist-info/METADATA
asyncio_cache-0.0.1.dist-info/WHEEL
asyncio_cache-0.0.1.dist-info/top_level.txt
asyncio_cache-0.0.1.dist-info/RECORD
