Metadata-Version: 2.1
Name: asyncio-cache
Version: 0.0.1
Summary: A python library for asyncio caches (like functools cache and lru_cache)
Home-page: https://github.com/matan1008/asyncio-cache
Author: Matan Perelman
License: UNKNOWN
Project-URL: asyncio-cache, https://github.com/matan1008/asyncio-cache
Platform: UNKNOWN
Classifier: Programming Language :: Python :: 3.6
Classifier: Programming Language :: Python :: 3.7
Classifier: Programming Language :: Python :: 3.8
Classifier: Programming Language :: Python :: 3.9
Classifier: Programming Language :: Python :: 3.10
License-File: LICENSE
